orbitalml/__init__.py
orbitalml/ast.py
orbitalml/sql.py
orbitalml/translate.py
orbitalml/translation.py
orbitalml/types.py
orbitalml-0.2.2.dist-info/licenses/LICENSE
orbitalml-0.2.2.dist-info/METADATA
orbitalml-0.2.2.dist-info/WHEEL
orbitalml-0.2.2.dist-info/top_level.txt
orbitalml-0.2.2.dist-info/RECORD
